{
  "product_id": "017679918301",
  "product_type": "phone",
  "comments": [
    {
      "id": 14974,
      "content": "Khi mua có thể trả góp không?",
      "creationTime": "2024-12-14T05:10:39.849000Z",
      "creationTimeDisplay": "6 tháng trước",
      "isAdministrator": false,
      "fullName": "Kỳ An",
      "likeCount": 0,
      "tags": ["chính sách trả góp"],
      "children": [
        {
          "id": 14975,
          "content": "Chào anh An\n\nOPPO A18 4GB 64GB giá ưu đãi chỉ từ 2.990.000 ₫ có chương trình trả góp với lãi suất 0%, hỗ trợ qua thẻ tín dụng và nhà tài chính, giúp anh dễ dàng sở hữu sản phẩm mà không lo về tài chính.\n\nNếu cần thêm thông tin khác anh gọi tổng đài miễn phí 18006601 hoặc có thể chat qua Zalo [tại đây](https://zalo.me/2659487666103055748). Để được hỗ trợ nhanh nhất ạ.\n\nThân mến!",
          "creationTime": "2024-12-14T05:11:36Z",
          "creationTimeDisplay": "6 tháng trước",
          "isAdministrator": true,
          "fullName": "Nguyễn Trung Hữu",
          "likeCount": 0,
          "tags": [],
          "children": [],
          "media": []
        }
      ],
      "media": []
    },
    {
      "id": 14956,
      "content": "Mặt hàng này ở Vĩnh Hưng hoàng mai còn ko ak",
      "creationTime": "2025-06-03T14:09:13.203000Z",
      "creationTimeDisplay": "7 ngày trước",
      "isAdministrator": false,
      "fullName": "Phạm toản ",
      "likeCount": 0,
      "tags": ["tình trạng hàng"],
      "children": [
        {
          "id": 14957,
          "content": "Chào anh Toàn,\n\nDạ sản phẩm OPPO A18 4GB 64GB có giá 2.890.000 ₫, đang có các ưu đãi như đổi điện thoại bàn phím/ĐT cũ/MTB cũ còn lên nguồn giảm 300,000đ, tặng phiếu mua hàng Phụ Kiện 100.000đ áp dụng đến 08/06, trả góp 0%. Ở Vĩnh Hưng Hoàng Mai bên em vẫn đang còn hàng.\n\nBên em xin phép liên hệ để tư vấn chi tiết hơn. Nếu cần thêm thông tin khác anh gọi tổng đài miễn phí 18006601 hoặc có thể chat qua Zalo [tại đây](https://zalo.me/2659487666103055748).\n\nThân mến!",
          "creationTime": "2025-06-03T14:11:57Z",
          "creationTimeDisplay": "7 ngày trước",
          "isAdministrator": true,
          "fullName": "Kien Nguyen",
          "likeCount": 0,
          "tags": [],
          "children": [],
          "media": []
        }
      ],
      "media": []
    },
    {
      "id": 14996,
      "content": "Pin trâu không ạ ",
      "creationTime": "2024-12-13T14:18:55.714000Z",
      "creationTimeDisplay": "6 tháng trước",
      "isAdministrator": false,
      "fullName": "Kiên Thành",
      "likeCount": 0,
      "tags": ["pin","hiệu năng"],
      "children": [
        {
          "id": 14997,
          "content": "Chào anh Thành,\n\nSản phẩm này được trang bị viên pin 5000mAh, giúp anh sử dụng cả ngày dài mà không lo hết pin. Nếu cần thêm thông tin khác anh gọi tổng đài miễn phí 18006601 hoặc có thể chat qua Zalo [tại đây](https://zalo.me/2659487666103055748) để được hỗ trợ nhanh nhất ạ.\n\nThân mến!",
          "creationTime": "2024-12-13T14:20:44Z",
          "creationTimeDisplay": "6 tháng trước",
          "isAdministrator": true,
          "fullName": "Nguyễn Trung Hữu",
          "likeCount": 0,
          "tags": [],
          "children": [],
          "media": []
        }
      ],
      "media": []
    }
  ]
}